problem/__init__.py
problem/admin.py
problem/api_views.py
problem/apps.py
problem/forms.py
problem/models.py
problem/serializers.py
problem/settings.py
problem/signals.py
problem/tests.py
problem/urls.py
problem/views.py
problem/migrations/0001_initial.py
problem/migrations/__init__.py
problem/templates/problem/problem_detail.html
problem/templates/problem/problem_form.html
problem/templates/problem/problem_list.html
django_problem-1.0.0.dist-info/LICENSE
django_problem-1.0.0.dist-info/METADATA
django_problem-1.0.0.dist-info/WHEEL
django_problem-1.0.0.dist-info/top_level.txt
django_problem-1.0.0.dist-info/RECORD
